mhealpy/__init__.py
mhealpy/_version.py
mhealpy/containers/__init__.py
mhealpy/containers/healpix_base.py
mhealpy/containers/healpix_map.py
mhealpy/pixelfunc/__init__.py
mhealpy/pixelfunc/moc.py
mhealpy/pixelfunc/single.py
mhealpy/plot/__init__.py
mhealpy/plot/axes.py
mhealpy/plot/util.py
mhealpy/util/__init__.py
mhealpy/util/signal.py
mhealpy-0.3.6.dist-info/licenses/LICENSE
mhealpy-0.3.6.dist-info/METADATA
mhealpy-0.3.6.dist-info/WHEEL
mhealpy-0.3.6.dist-info/top_level.txt
mhealpy-0.3.6.dist-info/RECORD
