Metadata-Version: 2.4
Name: mhealpy
Version: 0.3.6
Summary: Object-oriented healpy wrapper supporting multi-resolution maps
Home-page: https://gitlab.com/burstcube/HealpixMap
Author: Israel Martinez-Castellanos
Author-email: imc@umd.edu
License-File: LICENSE
Requires-Dist: healpy
Requires-Dist: matplotlib
Dynamic: author
Dynamic: author-email
Dynamic: description
Dynamic: description-content-type
Dynamic: home-page
Dynamic: license-file
Dynamic: requires-dist
Dynamic: summary
